pytest_locker/__init__.py
pytest_locker/fixtures.py
pytest_locker/py.typed
pytest_locker-0.3.0.dist-info/LICENSE
pytest_locker-0.3.0.dist-info/METADATA
pytest_locker-0.3.0.dist-info/WHEEL
pytest_locker-0.3.0.dist-info/RECORD
