Metadata-Version: 2.1
Name: pytest-locker
Version: 0.3.0
Summary:  Used to lock object during testing. Essentially changing assertions from being hard coded to asserting that nothing changed 
Home-page: https://pytest-locker.daanluttik.nl
License: MIT
Author: Luttik
Author-email: dtluttik@gmail.com
Requires-Python: >=3.9,<4.0
Classifier: License :: OSI Approved :: MIT License
Classifier: Programming Language :: Python :: 3
Classifier: Programming Language :: Python :: 3.9
Classifier: Programming Language :: Python :: 3.10
Classifier: Programming Language :: Python :: 3.11
Classifier: Programming Language :: Python :: 3.12
Classifier: Programming Language :: Python :: 3.13
Requires-Dist: pytest (>=5.4)
Project-URL: Documentation, https://pytest-locker.daanluttik.nl
Project-URL: Repository, https://github.com/Luttik/pytest-locker
